odoo/addons/git_base/LICENSE
odoo/addons/git_base/README.rst
odoo/addons/git_base/__init__.py
odoo/addons/git_base/__manifest__.py
odoo/addons/git_base/data/data.xml
odoo/addons/git_base/demo/demo.xml
odoo/addons/git_base/images/screen.png
odoo/addons/git_base/models/__init__.py
odoo/addons/git_base/models/git_account.py
odoo/addons/git_base/models/git_forge.py
odoo/addons/git_base/models/git_repo.py
odoo/addons/git_base/models/git_repo_branch.py
odoo/addons/git_base/models/git_repo_command.py
odoo/addons/git_base/models/git_repo_log.py
odoo/addons/git_base/security/ir.model.access.csv
odoo/addons/git_base/security/security.xml
odoo/addons/git_base/static/description/icon.png
odoo/addons/git_base/static/description/index.html
odoo/addons/git_base/static/src/css/style.css
odoo/addons/git_base/tests/__init__.py
odoo/addons/git_base/tests/test.txt
odoo/addons/git_base/tests/test.zip
odoo/addons/git_base/tests/test_git_repo.py
odoo/addons/git_base/views/git_account_views.xml
odoo/addons/git_base/views/git_forge_views.xml
odoo/addons/git_base/views/git_repo_cmd_views.xml
odoo/addons/git_base/views/git_repo_views.xml
odoo_addon_git_base-18.0.1.0.0.dist-info/METADATA
odoo_addon_git_base-18.0.1.0.0.dist-info/WHEEL
odoo_addon_git_base-18.0.1.0.0.dist-info/top_level.txt
odoo_addon_git_base-18.0.1.0.0.dist-info/RECORD
